bbii_decon/__init__.py
bbii_decon/_tests/__init__.py
bbii_decon/_tests/test_function.py
bbii_decon-0.0.1.dist-info/LICENSE
bbii_decon-0.0.1.dist-info/METADATA
bbii_decon-0.0.1.dist-info/WHEEL
bbii_decon-0.0.1.dist-info/entry_points.txt
bbii_decon-0.0.1.dist-info/top_level.txt
bbii_decon-0.0.1.dist-info/RECORD
