Metadata-Version: 2.1
Name: bbii-decon
Version: 0.0.1
Summary: Projected Barzilai-Borwein Image Deconvolution with Infeasible Iterates (BBii-Decon)
Home-page: https://github.com/gdellaire/bbii-decon
Author: Graham Dellaire, Robert Haase
Author-email: dellaire@Dal.Ca
License: BSD-3-Clause
Project-URL: Bug Tracker, https://github.com/gdellaire/bbii-decon/issues
Project-URL: Documentation, https://github.com/gdellaire/bbii-decon#README.md
Project-URL: Source Code, https://github.com/gdellaire/bbii-decon
Project-URL: User Support, https://github.com/gdellaire/bbii-decon/issues
Platform: UNKNOWN
Classifier: Development Status :: 2 - Pre-Alpha
Classifier: Intended Audience :: Developers
Classifier: Framework :: napari
Classifier: Topic :: Software Development :: Testing
Classifier: Programming Language :: Python
Classifier: Programming Language :: Python :: 3
Classifier: Programming Language :: Python :: 3.7
Classifier: Programming Language :: Python :: 3.8
Classifier: Programming Language :: Python :: 3.9
Classifier: Operating System :: OS Independent
Classifier: License :: OSI Approved :: BSD License
Requires-Python: >=3.7
License-File: LICENSE
Requires-Dist: napari-plugin-engine (>=0.1.4)
Requires-Dist: numpy
Requires-Dist: pypher
